evaluation/__init__.py
code_evaluation-0.1.dist-info/LICENSE
code_evaluation-0.1.dist-info/METADATA
code_evaluation-0.1.dist-info/WHEEL
code_evaluation-0.1.dist-info/top_level.txt
code_evaluation-0.1.dist-info/RECORD
