Metadata-Version: 2.1
Name: code-evaluation
Version: 0.1
Summary: A module to bundle xml using xpath
Home-page: https://github.com/divad1196/code_evaluation
Author: Gallay David
Author-email: davidtennis96@hotmail.com
License: UNKNOWN
Platform: UNKNOWN
Classifier: Programming Language :: Python :: 3
Classifier: License :: OSI Approved :: MIT License
Classifier: Operating System :: OS Independent
License-File: LICENSE
Requires-Dist: igraph
Requires-Dist: lxml
